tfrmaker/__init__.py
tfrmaker/display.py
tfrmaker/helper.py
tfrmaker/images.py
tfrmaker/py.typed
tfrmaker-0.0.2.dist-info/METADATA
tfrmaker-0.0.2.dist-info/WHEEL
tfrmaker-0.0.2.dist-info/licenses/LICENSE
tfrmaker-0.0.2.dist-info/RECORD
