Metadata-Version: 2.1
Name: tfrmaker
Version: 0.0.2
Summary: A Tensorflow TFRecord Utility Package
Project-URL: Homepage, https://github.com/csbasil/tfrmaker
Project-URL: Bug Tracker, https://github.com/csbasil/tfrmaker/issues
Author-email: "Basil C. Sunny" <csbasil@gmail.com>
License: MIT License
Classifier: License :: OSI Approved :: MIT License
Classifier: Operating System :: OS Independent
Classifier: Programming Language :: Python :: 3
Requires-Python: >=3.7
